eyelinkio/__init__.py
eyelinkio/edf/README.txt
eyelinkio/edf/__init__.py
eyelinkio/edf/_defines.py
eyelinkio/edf/_edf2py.py
eyelinkio/edf/read_edf.py
eyelinkio/tests/__init__.py
eyelinkio/tests/test_edf.py
eyelinkio/tests/data/test_2_raw.edf
eyelinkio/tests/data/test_raw.edf
eyelinkio/tests/data/test_raw_binocular.edf
eyelinkio/utils/__init__.py
eyelinkio/utils/check.py
eyelinkio/utils/utils.py
eyelinkio/utils/tests/__init__.py
libedfapi/linux/libedfapi.so
libedfapi/macos/edfapi.framework/edfapi
libedfapi/macos/edfapi.framework/Resources/Info.plist
libedfapi/windows/win32/edfapi.dll
libedfapi/windows/win64/edfapi64.dll
libedfapi/windows/win64/zlibwapi.dll
eyelinkio-0.3.0.dist-info/LICENSE
eyelinkio-0.3.0.dist-info/METADATA
eyelinkio-0.3.0.dist-info/WHEEL
eyelinkio-0.3.0.dist-info/top_level.txt
eyelinkio-0.3.0.dist-info/RECORD
