Metadata-Version: 2.1
Name: eyelinkio
Version: 0.3.0
Summary: A lightweight library for reading Eyelink Data Format files in Python.
Maintainer-email: Scott Huberty <seh33@uw.edu>
Project-URL: Homepage, https://scott-huberty.github.io/eyelinkio/
Project-URL: Download, https://pypi.org/project/eyelinkio/#files
Project-URL: Bug Tracker, https://github.com/scott-huberty/eyelinkio/issues
Project-URL: Documentation, https://scott-huberty.github.io/eyelinkio/
Project-URL: Source Code, https://github.com/scott-huberty/eyelinkio
Keywords: neuroscience,eyelink,eyetracking,SR Research
Classifier: Intended Audience :: Science/Research
Classifier: Intended Audience :: Developers
Classifier: Programming Language :: Python
Classifier: Topic :: Software Development
Classifier: Topic :: Scientific/Engineering
Classifier: Operating System :: Microsoft :: Windows
Classifier: Operating System :: POSIX
Classifier: Operating System :: Unix
Classifier: Operating System :: MacOS
Classifier: Programming Language :: Python :: 3
Requires-Python: >=3.9
License-File: LICENSE
Requires-Dist: numpy>=1.21.2
Provides-Extra: test
Requires-Dist: pytest>=8.0.0rc2; extra == "test"
Requires-Dist: pytest-cov; extra == "test"
Requires-Dist: pytest-timeout; extra == "test"
Requires-Dist: ruff; extra == "test"
Requires-Dist: numpydoc; extra == "test"
Requires-Dist: codespell; extra == "test"
Requires-Dist: tomli; python_version < "3.11" and extra == "test"
Provides-Extra: doc
Requires-Dist: sphinx>=6; extra == "doc"
Requires-Dist: numpydoc; extra == "doc"
Requires-Dist: pydata_sphinx_theme; extra == "doc"
Requires-Dist: sphinxemoji; extra == "doc"
Requires-Dist: sphinxcontrib-towncrier; extra == "doc"
Provides-Extra: full
Requires-Dist: pandas; extra == "full"
Requires-Dist: mne; extra == "full"
Provides-Extra: build
Requires-Dist: build; extra == "build"
Requires-Dist: twine; extra == "build"
Provides-Extra: dev
Requires-Dist: eyelinkio[build,doc,full,test]; extra == "dev"
